trivial/__init__.py
trivial/draw.py
trivial/dtypes.py
trivial/geometry.py
trivial/graphics.py
trivial/mesh.py
trivial/object.py
trivial/pipeline.py
trivial/proxy.py
trivial/texture.py
trivial/version.py
trivial/buffer/__init__.py
trivial/buffer/buffer.py
trivial/buffer/buffer_pointer.py
trivial/buffer/vertex_array.py
trivial/shader/__init__.py
trivial/shader/default.py
trivial/shader/enumerations.py
trivial/shader/glsl.py
trivial/shader/program.py
trivial/shader/shader.py
trivial/shader/variables.py
trivial_graphics-0.0.12.dist-info/licenses/LICENSE
trivial_graphics-0.0.12.dist-info/METADATA
trivial_graphics-0.0.12.dist-info/WHEEL
trivial_graphics-0.0.12.dist-info/top_level.txt
trivial_graphics-0.0.12.dist-info/RECORD
