Metadata-Version: 2.4
Name: trivial-graphics
Version: 0.0.12
Summary: Pythonic OpenGL Bindings
Home-page: https://github.com/takeiteasy/trivial-graphics
Author: George Watson
Author-email: George Watson <gigolo@hotmail.co.uk>
License: GPLv3
Project-URL: Homepage, https://github.com/takeiteasy/trivial-graphics
Project-URL: Issues, https://github.com/takeiteasy/trivial-graphics/issues
Platform: any
Classifier: Natural Language :: English
Classifier: Intended Audience :: Developers
Classifier: Operating System :: MacOS :: MacOS X
Classifier: Operating System :: Microsoft :: Windows
Classifier: Operating System :: POSIX
Classifier: Programming Language :: Python
Classifier: License :: OSI Approved :: GNU General Public License v3 (GPLv3)
Classifier: Topic :: Multimedia :: Graphics
Classifier: Topic :: Scientific/Engineering :: Mathematics
Classifier: Topic :: Software Development :: Libraries
Classifier: Topic :: Software Development :: Libraries :: Python Modules
Requires-Python: >=3.10
License-File: LICENSE
Requires-Dist: pyopengl==3.1.9
Requires-Dist: pyglsl==0.0.7
Requires-Dist: pillow==11.1.0
Dynamic: author
Dynamic: home-page
Dynamic: license-file
Dynamic: platform
